samna/__init__.py
samna-0.48.3.dist-info/licenses/LICENSE
samna-0.48.3.dist-info/licenses/NOTICE
samna-0.48.3.dist-info/METADATA
samna-0.48.3.dist-info/WHEEL
samna-0.48.3.dist-info/top_level.txt
samna-0.48.3.dist-info/RECORD
